setup.py
bin_gauss_distribution/Binomialdistribution.py
bin_gauss_distribution/Gaussiandistribution.py
bin_gauss_distribution/Generaldistribution.py
bin_gauss_distribution/__init__.py
bin_gauss_distribution.egg-info/PKG-INFO
bin_gauss_distribution.egg-info/SOURCES.txt
bin_gauss_distribution.egg-info/dependency_links.txt
bin_gauss_distribution.egg-info/not-zip-safe
bin_gauss_distribution.egg-info/top_level.txt