Metadata-Version: 1.0
Name: bin-gauss-distribution
Version: 1.1
Summary: Package for Binomial and Gaussian distributions
Home-page: UNKNOWN
Author: Teslim Olayiwola
Author-email: olayiwolateslim9@gmail.com
License: UNKNOWN
Platform: UNKNOWN
